ATflexipy/ATflexipy.py
ATflexipy/__init__.py
atflexipy-1.0.1.dist-info/licenses/LICENSE
atflexipy-1.0.1.dist-info/METADATA
atflexipy-1.0.1.dist-info/WHEEL
atflexipy-1.0.1.dist-info/top_level.txt
atflexipy-1.0.1.dist-info/RECORD
