Metadata-Version: 2.4
Name: ATflexipy
Version: 1.0.1
Summary: Flexible Python utilities for function/class overloading, logging, and runtime helpers.
Author: Avi Twil
Author-email: Avi Twil <avitwil@gmail.com>
License-Expression: MIT
Keywords: flexible,overload,decorator,logging,utilities
Classifier: Programming Language :: Python :: 3
Classifier: Operating System :: OS Independent
Requires-Python: >=3.10
License-File: LICENSE
Dynamic: license-file
